{
  "generatedAt": "2026-04-19T21:54:23.097Z",
  "plugins": [
    {
      "pluginId": "chromaspace",
      "displayName": "Chromaspace",
      "manifestUrl": "https://moazelgabry.github.io/Moaz-Elgabry-plugins/plugins/chromaspace/stable.json"
    },
    {
      "pluginId": "lensdiff",
      "displayName": "LensDiff",
      "manifestUrl": "https://moazelgabry.github.io/Moaz-Elgabry-plugins/plugins/lensdiff/stable.json"
    },
    {
      "pluginId": "me-opendrt",
      "displayName": "ME_OpenDRT",
      "manifestUrl": "https://moazelgabry.github.io/Moaz-Elgabry-plugins/plugins/me-opendrt/stable.json"
    }
  ]
}
